simplelabel/__init__.py
simplelabel/__main__.py
simplelabel/core/__init__.py
simplelabel/core/mapper.py
simplelabel/core/parser.py
simplelabel/core/rule.py
simplelabel/utils/__init__.py
simplelabel/utils/generator.py
simplelabel/utils/label.py
simplelabel/utils/tools.py
simplelabel-1.3.0b0.dist-info/METADATA
simplelabel-1.3.0b0.dist-info/WHEEL
simplelabel-1.3.0b0.dist-info/entry_points.txt
simplelabel-1.3.0b0.dist-info/RECORD
